EasyKnn/__init__.py
EasyKnn/dataset.py
EasyKnn/errors.py
EasyKnn/neighbors.py
EasyKnn/plan.py
EasyKnn/point.py
EasyKnn/value.py
EasyKnn/weight.py
EasyPyKnn-0.2.0.dist-info/LICENSE
EasyPyKnn-0.2.0.dist-info/METADATA
EasyPyKnn-0.2.0.dist-info/WHEEL
EasyPyKnn-0.2.0.dist-info/top_level.txt
EasyPyKnn-0.2.0.dist-info/RECORD
