Metadata-Version: 2.1
Name: EasyPyKnn
Version: 0.2.0
Summary: An easy educational implementation of the K nearest neighbors algorithm
Author-email: v0ltis <hello@voltis.me>
Project-URL: Homepage, https://github.com/v0ltis/EasyKNN
Project-URL: Bug Tracker, https://github.com/v0ltis/EasyKNN/issues
Classifier: Development Status :: 4 - Beta
Classifier: Intended Audience :: Education
Classifier: Topic :: Education
Classifier: Programming Language :: Python :: 3
Classifier: License :: OSI Approved :: MIT License
Classifier: Operating System :: OS Independent
Classifier: Natural Language :: English
Requires-Python: >=3.6
License-File: LICENSE
